evalcache/__init__.py
evalcache/dircache.py
evalcache/dircache_v2.py
evalcache/funcarg.py
evalcache/lazy.py
evalcache/lazyfile.py
evalcache/util.py
evalcache-1.14.0.dist-info/METADATA
evalcache-1.14.0.dist-info/WHEEL
evalcache-1.14.0.dist-info/top_level.txt
evalcache-1.14.0.dist-info/RECORD
