Metadata-Version: 2.1
Name: evalcache
Version: 1.14.0
Summary: Lazy computing tree cache library
Home-page: https://github.com/mirmik/evalcache
Author: mirmik
Author-email: mirmikns@yandex.ru
License: MIT
Keywords: caching,lazy
Platform: UNKNOWN
